abm/__init__.py
abm/decor.py
abm/exec.py
abm/interactive.py
abm/open_edx_grader.py
abm/cli/__init__.py
abm/cli/exec.py
Agent_Behavior_Model-23.1.25.dist-info/METADATA
Agent_Behavior_Model-23.1.25.dist-info/WHEEL
Agent_Behavior_Model-23.1.25.dist-info/eager_resources.txt
Agent_Behavior_Model-23.1.25.dist-info/entry_points.txt
Agent_Behavior_Model-23.1.25.dist-info/top_level.txt
Agent_Behavior_Model-23.1.25.dist-info/zip-safe
Agent_Behavior_Model-23.1.25.dist-info/RECORD
