Metadata-Version: 2.1
Name: Agent-Behavior-Model
Version: 23.1.25
Summary: Agent Behavior Model
Home-page: https://GitHub.com/IoT-Robotics/Agent-Behavior-Model
Download-URL: https://GitHub.com/IoT-Robotics/Agent-Behavior-Model/archive/main.zip
Author: The Vinh LUONG (LƯƠNG Thế Vinh)
Author-email: "The Vinh LUONG (LƯƠNG Thế Vinh)" <Vinh@STEAMforVietnam.org>
Maintainer: STEAM for Vietnam Foundation: Robotics & AI Educational Initative
Maintainer-email: "The Vinh LUONG (LƯƠNG Thế Vinh)" <Vinh@STEAMforVietnam.org>, "STEAM for Vietnam Foundation: Robotics & AI Educational Initative" <Edu.Robotics@STEAMforVietnam.org>
License: MIT
Project-URL: Homepage, https://GitHub.com/IoT-Robotics/Agent-Behavior-Model
Project-URL: Documentation, https://GitHub.com/IoT-Robotics/Agent-Behavior-Model
Project-URL: GitHub, https://GitHub.com/IoT-Robotics/Agent-Behavior-Model
Project-URL: Repository, https://GitHub.com/IoT-Robotics/Agent-Behavior-Model
Keywords: agent,behavior,behaviour,model,modeling,modelling
Classifier: Development Status :: 4 - Beta
Classifier: Framework :: Robot Framework
Classifier: Framework :: Robot Framework :: Library
Classifier: Framework :: Robot Framework :: Tool
Classifier: Intended Audience :: Education
Classifier: Operating System :: MacOS
Classifier: Operating System :: MacOS :: MacOS X
Classifier: Operating System :: Microsoft :: Windows
Classifier: Operating System :: POSIX :: Linux
Classifier: Programming Language :: Python
Classifier: Programming Language :: Python :: 3
Classifier: Programming Language :: Python :: 3.11
Classifier: Programming Language :: Python :: 3.12
Classifier: Topic :: Education
Classifier: Topic :: Scientific/Engineering
Classifier: Topic :: Software Development :: Libraries :: Python Modules
Requires-Python: >=3.11
Requires-Dist: CLICK (>=8.1.3)
Requires-Dist: Decorator (>=5.1.1)
Requires-Dist: Wrapt (>=1.14.1)
Requires-Dist: EdX-CodeJail (>=3.3.1)
Provides-Extra: devtest
Requires-Dist: Nose2 (>=0.12.0) ; extra == 'devtest'
Requires-Dist: PyTest (>=7.2.1) ; extra == 'devtest'
Provides-Extra: publish
Requires-Dist: Build (>=0.10.0) ; extra == 'publish'
Requires-Dist: Twine (>=4.0.2) ; extra == 'publish'
